first_pkg/__init__.py
first_pkg/foo.py
fooyou-0.0.1.dist-info/LICENSE
fooyou-0.0.1.dist-info/METADATA
fooyou-0.0.1.dist-info/WHEEL
fooyou-0.0.1.dist-info/top_level.txt
fooyou-0.0.1.dist-info/RECORD
