Metadata-Version: 2.1
Name: fooyou
Version: 0.0.1
Summary: my first pypi package
Home-page: UNKNOWN
Author: khalid Mazroe
Author-email: khalid.almazrouai@gmail.com
License: UNKNOWN
Platform: UNKNOWN
Classifier: Programming Language :: Python :: 3
Classifier: License :: OSI Approved :: MIT License
Classifier: Operating System :: OS Independent
Requires-Python: >=3.6
